torchsom/__init__.py
torchsom/version.py
torchsom/configs/__init__.py
torchsom/configs/som_config.py
torchsom/core/__init__.py
torchsom/core/base_som.py
torchsom/core/som.py
torchsom/core/growing/__init__.py
torchsom/core/growing/components.py
torchsom/core/growing/growing_som.py
torchsom/core/hierarchical/__init__.py
torchsom/core/hierarchical/components.py
torchsom/core/hierarchical/hierarchical_som.py
torchsom/utils/__init__.py
torchsom/utils/clustering.py
torchsom/utils/decay.py
torchsom/utils/distances.py
torchsom/utils/grid.py
torchsom/utils/hexagonal_coordinates.py
torchsom/utils/initialization.py
torchsom/utils/maps.py
torchsom/utils/metrics.py
torchsom/utils/neighborhood.py
torchsom/utils/topology.py
torchsom/visualization/__init__.py
torchsom/visualization/base.py
torchsom/visualization/base_visualizer.py
torchsom/visualization/clustering.py
torchsom/visualization/config.py
torchsom/visualization/hexagonal.py
torchsom/visualization/hexagonal_utils.py
torchsom/visualization/rectangular.py
torchsom-1.1.1.dist-info/licenses/LICENSE
torchsom-1.1.1.dist-info/METADATA
torchsom-1.1.1.dist-info/WHEEL
torchsom-1.1.1.dist-info/top_level.txt
torchsom-1.1.1.dist-info/RECORD
