Metadata-Version: 2.4
Name: torchsom
Version: 1.1.1
Summary: torchsom: The Reference PyTorch Library for Self-Organizing Maps
Author-email: Louis Berthier <louis-desire-romeo.berthier@michelin.com>
Maintainer-email: Louis Berthier <louis-desire-romeo.berthier@michelin.com>
Project-URL: Source, https://github.com/michelin/torchsom
Project-URL: Documentation, https://opensource.michelin.io/TorchSOM/
Project-URL: Tracker, https://github.com/michelin/TorchSOM/issues
Project-URL: License, https://github.com/michelin/TorchSOM/blob/main/LICENSE
Project-URL: Contributing, https://github.com/michelin/TorchSOM/blob/main/CONTRIBUTING.md
Project-URL: Code of Conduct, https://github.com/michelin/TorchSOM/blob/main/CODE_OF_CONDUCT.md
Project-URL: Citation, https://github.com/michelin/TorchSOM/blob/main/CITATION.cff
Keywords: Self-Organizing-Maps,SOM,PyTorch,Machine-Learning,Unsupervised-Learning,Dimensionality-Reduction,Clustering,Data-Visualization,Just-In-Time-Learning
Classifier: Development Status :: 4 - Beta
Classifier: Natural Language :: English
Classifier: Operating System :: OS Independent
Classifier: Intended Audience :: Developers
Classifier: Intended Audience :: Healthcare Industry
Classifier: Intended Audience :: Manufacturing
Classifier: Intended Audience :: Science/Research
Classifier: Topic :: Scientific/Engineering :: Artificial Intelligence
Classifier: Topic :: Scientific/Engineering :: Information Analysis
Classifier: Topic :: Scientific/Engineering :: Visualization
Classifier: Topic :: Software Development :: Libraries
Classifier: Topic :: Software Development :: Testing :: Unit
Classifier: Topic :: Software Development :: Version Control :: Git
Classifier: Programming Language :: Python
Classifier: Programming Language :: Python :: 3.9
Classifier: Programming Language :: Python :: 3.10
Classifier: Programming Language :: Python :: 3.11
Classifier: License :: OSI Approved :: Apache Software License
Requires-Python: >=3.9
License-File: LICENSE
Requires-Dist: torch
Requires-Dist: numpy
Requires-Dist: matplotlib
Requires-Dist: tqdm
Requires-Dist: pydantic
Requires-Dist: hdbscan
Requires-Dist: scikit-learn
Provides-Extra: dev
Requires-Dist: pandas; extra == "dev"
Requires-Dist: openpyxl; extra == "dev"
Requires-Dist: black; extra == "dev"
Requires-Dist: isort; extra == "dev"
Requires-Dist: rich; extra == "dev"
Requires-Dist: typing_extensions; extra == "dev"
Requires-Dist: build; extra == "dev"
Requires-Dist: twine; extra == "dev"
Requires-Dist: commitizen; extra == "dev"
Requires-Dist: notebook; extra == "dev"
Requires-Dist: pyyaml; extra == "dev"
Provides-Extra: tests
Requires-Dist: pytest; extra == "tests"
Requires-Dist: pytest-cov; extra == "tests"
Requires-Dist: pytest-html; extra == "tests"
Requires-Dist: pytest-xdist; extra == "tests"
Requires-Dist: pytest-timeout; extra == "tests"
Provides-Extra: docs
Requires-Dist: sphinx; extra == "docs"
Requires-Dist: sphinx-rtd-theme; extra == "docs"
Requires-Dist: sphinx-autodoc-typehints; extra == "docs"
Requires-Dist: sphinx-copybutton; extra == "docs"
Requires-Dist: pydocstyle; extra == "docs"
Requires-Dist: interrogate; extra == "docs"
Provides-Extra: security
Requires-Dist: bandit[toml]; extra == "security"
Requires-Dist: safety; extra == "security"
Requires-Dist: pip-audit; extra == "security"
Requires-Dist: pip-tools; extra == "security"
Provides-Extra: linting
Requires-Dist: ruff; extra == "linting"
Requires-Dist: mypy; extra == "linting"
Requires-Dist: radon; extra == "linting"
Requires-Dist: certifi; extra == "linting"
Provides-Extra: all
Requires-Dist: pandas; extra == "all"
Requires-Dist: openpyxl; extra == "all"
Requires-Dist: black; extra == "all"
Requires-Dist: isort; extra == "all"
Requires-Dist: rich; extra == "all"
Requires-Dist: typing_extensions; extra == "all"
Requires-Dist: build; extra == "all"
Requires-Dist: twine; extra == "all"
Requires-Dist: commitizen; extra == "all"
Requires-Dist: notebook; extra == "all"
Requires-Dist: pyyaml; extra == "all"
Requires-Dist: pytest; extra == "all"
Requires-Dist: pytest-cov; extra == "all"
Requires-Dist: pytest-html; extra == "all"
Requires-Dist: pytest-xdist; extra == "all"
Requires-Dist: pytest-timeout; extra == "all"
Requires-Dist: sphinx; extra == "all"
Requires-Dist: sphinx-rtd-theme; extra == "all"
Requires-Dist: sphinx-autodoc-typehints; extra == "all"
Requires-Dist: sphinx-copybutton; extra == "all"
Requires-Dist: pydocstyle; extra == "all"
Requires-Dist: interrogate; extra == "all"
Requires-Dist: bandit[toml]; extra == "all"
Requires-Dist: safety; extra == "all"
Requires-Dist: pip-audit; extra == "all"
Requires-Dist: pip-tools; extra == "all"
Requires-Dist: ruff; extra == "all"
Requires-Dist: mypy; extra == "all"
Requires-Dist: radon; extra == "all"
Requires-Dist: certifi; extra == "all"
Dynamic: license-file
